pyfranc/__init__.py
pyfranc/data.py
pyfranc/expressions.py
pyfranc/franc.py
pyfranc/iso639.py
pyfranc/n_gram.py
pyfranc/pyfranc_cli.py
pyfranc/trigram_utils.py
pyfranc/tests/api.py
pyfranc/tests/cli.py
pyfranc/tests/fixtures.py
pyfranc-0.2.3.dist-info/LICENSE
pyfranc-0.2.3.dist-info/METADATA
pyfranc-0.2.3.dist-info/WHEEL
pyfranc-0.2.3.dist-info/entry_points.txt
pyfranc-0.2.3.dist-info/top_level.txt
pyfranc-0.2.3.dist-info/RECORD
