Metadata-Version: 2.1
Name: pyfranc
Version: 0.2.3
Summary: Text language detection basic on trigrams.
Home-page: https://github.com/cyb3rk0tik/pyfranc
Author: cyb3rk0tik
Author-email: cyberkotik@riseup.net
License: MIT
Classifier: Programming Language :: Python :: 3
Classifier: License :: OSI Approved :: MIT License
Classifier: Operating System :: OS Independent
Requires-Python: >=3
License-File: LICENSE
